storagetwitter.py
twitter_new.py
twittercooc-1.0.0.dist-info/DESCRIPTION.rst
twittercooc-1.0.0.dist-info/METADATA
twittercooc-1.0.0.dist-info/RECORD
twittercooc-1.0.0.dist-info/WHEEL
twittercooc-1.0.0.dist-info/metadata.json
twittercooc-1.0.0.dist-info/top_level.txt
