Metadata-Version: 2.0
Name: twittercooc
Version: 1.0.0
Summary: UNKNOWN
Home-page: UNKNOWN
Author: Meysam Kheyrollah
Author-email: meysamkheyrollahnejad@gmail.com
License: UNKNOWN
Platform: UNKNOWN
Requires-Dist: json
Requires-Dist: pandas
Requires-Dist: pymysql
Requires-Dist: requests
